__init__.py
main.py
replace_text-1.1.0.dist-info/LICENSE
replace_text-1.1.0.dist-info/METADATA
replace_text-1.1.0.dist-info/WHEEL
replace_text-1.1.0.dist-info/entry_points.txt
replace_text-1.1.0.dist-info/top_level.txt
replace_text-1.1.0.dist-info/RECORD
