Metadata-Version: 2.1
Name: replace-text
Version: 1.1.0
License-File: LICENSE
